gickup/__init__.py
gickup/__main__.py
gickup/gblib.py
gickup/helpers.py
gickup/repoindex.py
gickup-1.0.dist-info/DESCRIPTION.rst
gickup-1.0.dist-info/LICENSE.txt
gickup-1.0.dist-info/METADATA
gickup-1.0.dist-info/RECORD
gickup-1.0.dist-info/WHEEL
gickup-1.0.dist-info/entry_points.txt
gickup-1.0.dist-info/metadata.json
gickup-1.0.dist-info/top_level.txt
