Metadata-Version: 2.0
Name: gickup
Version: 1.0
Summary: Automatic git backup script for multiple repositories
Home-page: https://github.com/tu500/gickup
Author: Philip Matura
Author-email: philip.m@tura-home.de
License: AGPLv3+
Keywords: git backup
Platform: UNKNOWN
Classifier: Development Status :: 5 - Production/Stable
Classifier: Environment :: Console
Classifier: License :: OSI Approved :: GNU Affero General Public License v3 or later (AGPLv3+)
Classifier: Operating System :: POSIX :: Linux
Classifier: Programming Language :: Python :: 3 :: Only
Classifier: Topic :: Software Development :: Version Control :: Git
Classifier: Topic :: System :: Archiving :: Backup
